{"nodes": [{"id": "web_src_entities_selectors_userselect_tsx", "label": "UserSelect.tsx", "file_type": "code", "source_file": "web\\src\\entities\\selectors\\UserSelect.tsx", "source_location": "L1"}, {"id": "userselect_includesrole", "label": "includesRole()", "file_type": "code", "source_file": "web\\src\\entities\\selectors\\UserSelect.tsx", "source_location": "L32"}], "edges": [{"source": "web_src_entities_selectors_userselect_tsx", "target": "react", "relation": "imports_from", "confidence": "EXTRACTED", "source_file": "web\\src\\entities\\selectors\\UserSelect.tsx", "source_location": "L3", "weight": 1.0}, {"source": "web_src_entities_selectors_userselect_tsx", "target": "useusers", "relation": "imports_from", "confidence": "EXTRACTED", "source_file": "web\\src\\entities\\selectors\\UserSelect.tsx", "source_location": "L4", "weight": 1.0}, {"source": "web_src_entities_selectors_userselect_tsx", "target": "roles", "relation": "imports_from", "confidence": "EXTRACTED", "source_file": "web\\src\\entities\\selectors\\UserSelect.tsx", "source_location": "L5", "weight": 1.0}, {"source": "web_src_entities_selectors_userselect_tsx", "target": "web_src_entities_selectors_shared", "relation": "imports_from", "confidence": "EXTRACTED", "source_file": "web\\src\\entities\\selectors\\UserSelect.tsx", "source_location": "L6", "weight": 1.0}, {"source": "web_src_entities_selectors_userselect_tsx", "target": "userselect_includesrole", "relation": "contains", "confidence": "EXTRACTED", "source_file": "web\\src\\entities\\selectors\\UserSelect.tsx", "source_location": "L32", "weight": 1.0}]}