{"nodes": [{"id": "web_src_lib_runtimeenv_ts", "label": "runtimeEnv.ts", "file_type": "code", "source_file": "web\\src\\lib\\runtimeEnv.ts", "source_location": "L1"}, {"id": "runtimeenv_isemulatorrequested", "label": "isEmulatorRequested()", "file_type": "code", "source_file": "web\\src\\lib\\runtimeEnv.ts", "source_location": "L3"}, {"id": "runtimeenv_isbrowserlocalhost", "label": "isBrowserLocalhost()", "file_type": "code", "source_file": "web\\src\\lib\\runtimeEnv.ts", "source_location": "L10"}, {"id": "runtimeenv_shoulduseemulators", "label": "shouldUseEmulators()", "file_type": "code", "source_file": "web\\src\\lib\\runtimeEnv.ts", "source_location": "L16"}], "edges": [{"source": "web_src_lib_runtimeenv_ts", "target": "runtimeenv_isemulatorrequested", "relation": "contains", "confidence": "EXTRACTED", "source_file": "web\\src\\lib\\runtimeEnv.ts", "source_location": "L3", "weight": 1.0}, {"source": "web_src_lib_runtimeenv_ts", "target": "runtimeenv_isbrowserlocalhost", "relation": "contains", "confidence": "EXTRACTED", "source_file": "web\\src\\lib\\runtimeEnv.ts", "source_location": "L10", "weight": 1.0}, {"source": "web_src_lib_runtimeenv_ts", "target": "runtimeenv_shoulduseemulators", "relation": "contains", "confidence": "EXTRACTED", "source_file": "web\\src\\lib\\runtimeEnv.ts", "source_location": "L16", "weight": 1.0}, {"source": "runtimeenv_shoulduseemulators", "target": "runtimeenv_isemulatorrequested", "relation": "calls", "confidence": "EXTRACTED", "source_file": "web\\src\\lib\\runtimeEnv.ts", "source_location": "L17", "weight": 1.0}, {"source": "runtimeenv_shoulduseemulators", "target": "runtimeenv_isbrowserlocalhost", "relation": "calls", "confidence": "EXTRACTED", "source_file": "web\\src\\lib\\runtimeEnv.ts", "source_location": "L19", "weight": 1.0}]}