{"nodes": [{"id": "web_src_features_games_registry_ts", "label": "registry.ts", "file_type": "code", "source_file": "web\\src\\features\\games\\registry.ts", "source_location": "L1"}, {"id": "registry_getgamebyid", "label": "getGameById()", "file_type": "code", "source_file": "web\\src\\features\\games\\registry.ts", "source_location": "L91"}], "edges": [{"source": "web_src_features_games_registry_ts", "target": "react", "relation": "imports_from", "confidence": "EXTRACTED", "source_file": "web\\src\\features\\games\\registry.ts", "source_location": "L3", "weight": 1.0}, {"source": "web_src_features_games_registry_ts", "target": "web_src_features_games_runner_runnergame", "relation": "imports_from", "confidence": "EXTRACTED", "source_file": "web\\src\\features\\games\\registry.ts", "source_location": "L4", "weight": 1.0}, {"source": "web_src_features_games_registry_ts", "target": "web_src_features_games_snake_snakegame", "relation": "imports_from", "confidence": "EXTRACTED", "source_file": "web\\src\\features\\games\\registry.ts", "source_location": "L5", "weight": 1.0}, {"source": "web_src_features_games_registry_ts", "target": "web_src_features_games_space_spaceinvadersgame", "relation": "imports_from", "confidence": "EXTRACTED", "source_file": "web\\src\\features\\games\\registry.ts", "source_location": "L6", "weight": 1.0}, {"source": "web_src_features_games_registry_ts", "target": "web_src_features_games_tower_towerdefensegame", "relation": "imports_from", "confidence": "EXTRACTED", "source_file": "web\\src\\features\\games\\registry.ts", "source_location": "L7", "weight": 1.0}, {"source": "web_src_features_games_registry_ts", "target": "registry_getgamebyid", "relation": "contains", "confidence": "EXTRACTED", "source_file": "web\\src\\features\\games\\registry.ts", "source_location": "L91", "weight": 1.0}]}